[
  {
    "op": "addmerge",
    "path": "/variantgroups/-",
    "value": {
      "code": "rock",
      "loadFromProperties": "conquestgeology:block/rockwithdeposit"
    },
    "file": "game:blocktypes/stone/ore-ungraded.json",
    "side": "Server"
  },
  {
    "op": "replace",
    "path": "/allowedVariants",
    "value": [
      "ore-flint-chalk*",
      "ore-flint-chert",
      "ore-flint-limestone*",

      "ore-alum-andesite*",
      "ore-alum-bauxite",
      "ore-alum-dacite*",
      "ore-alum-limestone*",
      "ore-alum-rhyolite*",
      "ore-alum-shale",
      "ore-alum-tuff*",

      "ore-borax-claystone",
      "ore-borax-mudstone*",
      "ore-borax-sandstone*",
      "ore-borax-shale",
      "ore-borax-tuff*",

      "ore-cinnabar-andesite*",
      "ore-cinnabar-basalt*",
      "ore-cinnabar-chert",
      "ore-cinnabar-dacite*",
      "ore-cinnabar-graywacke",
      "ore-cinnabar-limestone*",
      "ore-cinnabar-quartzite*",
      "ore-cinnabar-rhyolite*",
      "ore-cinnabar-schist*",
      "ore-cinnabar-slate*",

      "ore-fluorite-granite*",
      "ore-fluorite-limestone*",
      "ore-fluorite-*marble*",

      "ore-graphite-claystone",
      "ore-graphite-gneiss*",
      "ore-graphite-granite*",
      "ore-graphite-limestone*",
      "ore-graphite-*marble*",
      "ore-graphite-peridotite",
      "ore-graphite-phyllite",
      "ore-graphite-quartzite*",
      "ore-graphite-schist*",
      "ore-graphite-slate*",

      "ore-kernite-claystone",
      "ore-kernite-shale",

      "ore-lapislazuli-limestone*",
      "ore-lapislazuli-*marble*",

      "ore-olivine-basalt*",
      "ore-olivine-kimberlite",
      "ore-olivine-peridotite",
      "ore-olivine-serpentinite*",

      "ore-phosphorite-chalk*",
      "ore-phosphorite-chert",
      "ore-phosphorite-limestone*",
      "ore-phosphorite-mudstone*",
      "ore-phosphorite-shale",
      
      "ore-quartz-andesite*",
      "ore-quartz-dacite*",
      "ore-quartz-gneiss*",
      "ore-quartz-granite*",
      "ore-quartz-limestone*",
      "ore-quartz-marble*",
      "ore-quartz-*marble",
      "ore-quartz-quartzite*",
      "ore-quartz-rhyolite*",
      "ore-quartz-sandstone*",
      "ore-quartz-schist*",
      "ore-quartz-tuff*",
      "ore-quartz_wolframite-granite*",

      "ore-sulfur-basalt*",
      "ore-sulfur-claystone",
      "ore-sulfur-dacite*",
      "ore-sulfur-halite",
      "ore-sulfur-limestone*",
      "ore-sulfur-*marble*",
      "ore-sulfur-quartzite*",
      "ore-sulfur-rhyolite*",
      
      "ore-sylvite-halite",

      "ore-olivine-peridotite",

      "ore-lignite-claystone",
      "ore-lignite-conglomerate",
      "ore-lignite-graywacke",
      "ore-lignite-limestone*",
      "ore-lignite-mudstone*",
      "ore-lignite-sandstone*",
      "ore-lignite-shale",
      "ore-lignite-claystone",
      "ore-lignite-conglomerate",
      "ore-lignite-graywacke",
      "ore-lignite-limestone*",
      "ore-lignite-mudstone*",
      "ore-lignite-sandstone*",
      "ore-lignite-shale",

      "ore-bituminouscoal-claystone",
      "ore-bituminouscoal-conglomerate",
      "ore-bituminouscoal-graywacke",
      "ore-bituminouscoal-limestone*",
      "ore-bituminouscoal-mudstone*",
      "ore-bituminouscoal-sandstone*",
      "ore-bituminouscoal-shale",
      "ore-bituminouscoal-claystone",
      "ore-bituminouscoal-conglomerate",
      "ore-bituminouscoal-graywacke",
      "ore-bituminouscoal-limestone*",
      "ore-bituminouscoal-mudstone*",
      "ore-bituminouscoal-sandstone*",
      "ore-bituminouscoal-shale",

      "ore-anthracite-claystone",
      "ore-anthracite-conglomerate",
      "ore-anthracite-graywacke",
      "ore-anthracite-limestone*",
      "ore-anthracite-mudstone*",
      "ore-anthracite-sandstone*",
      "ore-anthracite-shale",
      "ore-anthracite-claystone",
      "ore-anthracite-conglomerate",
      "ore-anthracite-graywacke",
      "ore-anthracite-mudstone*",
      "ore-anthracite-sandstone*",
      "ore-anthracite-shale",
      "ore-anthracite-phyllite",
      "ore-anthracite-quartzite*",
      "ore-anthracite-slate*"
    ],
    "file": "game:blocktypes/stone/ore-ungraded.json",
    "side": "Server"
  }
]